ibm_schematics/__init__.py
ibm_schematics/common.py
ibm_schematics/schematics_2_0_api_v2.py
ibm_schematics/schematics_v1.py
ibm_schematics/version.py
ibm_schematics-2.0.0.dist-info/LICENSE
ibm_schematics-2.0.0.dist-info/METADATA
ibm_schematics-2.0.0.dist-info/WHEEL
ibm_schematics-2.0.0.dist-info/top_level.txt
ibm_schematics-2.0.0.dist-info/zip-safe
ibm_schematics-2.0.0.dist-info/RECORD
