Metadata-Version: 2.1
Name: ibm-schematics
Version: 2.0.0
Summary: IBM Cloud Schematics Python SDK
Home-page: https://github.com/IBM/schematics-python-sdk.git
Author: IBM
Author-email: nvenkatesh.27@gmail.com
License: Apache 2.0
Keywords: ibm_schematics
Platform: UNKNOWN
Classifier: Programming Language :: Python
Classifier: Programming Language :: Python :: 3
Classifier: Programming Language :: Python :: 3.5
Classifier: Programming Language :: Python :: 3.6
Classifier: Programming Language :: Python :: 3.7
Classifier: Programming Language :: Python :: 3.8
Classifier: Development Status :: 4 - Beta
Classifier: Intended Audience :: Developers
Classifier: License :: OSI Approved :: Apache Software License
Classifier: Operating System :: OS Independent
Classifier: Topic :: Software Development :: Libraries :: Python Modules
Classifier: Topic :: Software Development :: Libraries :: Application Frameworks
Requires-Dist: requests (<3.0,>=2.24.0)
Requires-Dist: python-dateutil (<3.0.0,>=2.5.3)
Requires-Dist: ibm-cloud-sdk-core (<4.0.0,>=3.10.1)
